LICENSE
MANIFEST.in
setup.py
django_filetransfers.egg-info/PKG-INFO
django_filetransfers.egg-info/SOURCES.txt
django_filetransfers.egg-info/dependency_links.txt
django_filetransfers.egg-info/top_level.txt
filetransfers/__init__.py
filetransfers/api.py
filetransfers/backends/__init__.py
filetransfers/backends/base_url.py
filetransfers/backends/default.py
filetransfers/backends/delegate.py
filetransfers/backends/url.py
filetransfers/backends/xsendfile.py
filetransfers/templatetags/__init__.py
filetransfers/templatetags/filetransfers.py