Metadata-Version: 1.0
Name: django-filetransfers
Version: 0.1.0
Summary: Helper for writing reusable Django apps that handle uploads and downloads
Home-page: http://www.allbuttonspressed.com/projects/django-filetransfers
Author: Waldemar Kornewald
Author-email: UNKNOWN
License: UNKNOWN
Platform: any
